powerdrill/__init__.py
powerdrill/base.py
powerdrill/utils.py
sqlalchemy_powerdrill-0.3.0.dist-info/METADATA
sqlalchemy_powerdrill-0.3.0.dist-info/WHEEL
sqlalchemy_powerdrill-0.3.0.dist-info/entry_points.txt
sqlalchemy_powerdrill-0.3.0.dist-info/top_level.txt
sqlalchemy_powerdrill-0.3.0.dist-info/RECORD
