Metadata-Version: 2.2
Name: sqlalchemy-powerdrill
Version: 0.3.0
Summary: SQLAlchemy dialect for PowerDrill
Home-page: https://github.com/powerdrill/powerdrill-sqlalchemy
Author: Powerdrill AI
Author-email: support@powerdrill.ai
Classifier: Development Status :: 3 - Alpha
Classifier: Intended Audience :: Developers
Classifier: License :: OSI Approved :: MIT License
Classifier: Programming Language :: Python :: 3
Classifier: Programming Language :: Python :: 3.7
Classifier: Programming Language :: Python :: 3.8
Classifier: Programming Language :: Python :: 3.9
Classifier: Programming Language :: Python :: 3.10
Requires-Python: >=3.7
Requires-Dist: sqlalchemy<2.0.0,>=1.4.0
Requires-Dist: requests>=2.31.0
Dynamic: author
Dynamic: author-email
Dynamic: classifier
Dynamic: description
Dynamic: description-content-type
Dynamic: home-page
Dynamic: requires-dist
Dynamic: requires-python
Dynamic: summary
